ddt.py
ddt-1.7.1.dist-info/LICENSE.md
ddt-1.7.1.dist-info/METADATA
ddt-1.7.1.dist-info/WHEEL
ddt-1.7.1.dist-info/top_level.txt
ddt-1.7.1.dist-info/RECORD
